{
  "aracaju": 486,
  "belem": 1636,
  "beloHorizonte": 1726,
  "boaVista": 3067,
  "brasilia": 1716,
  "campoGrande": 2593,
  "cuiaba": 2495,
  "curitiba": 2545,
  "florianopolis": 2693,
  "fortaleza": 555,
  "goiania": 1889,
  "joaoPessoa": 0,
  "macapa": 1964,
  "maceio": 299,
  "manaus": 2819,
  "natal": 151,
  "palmas": 1521,
  "portoAlegre": 3066,
  "portoVelho": 3200,
  "recife": 104,
  "rioBranco": 3632,
  "rioDeJaneiro": 1968,
  "salvador": 763,
  "saoLuis": 1162,
  "saoPaulo": 2216,
  "teresina": 905,
  "vitoria": 1581
}
